{
    "Ar36": {
        "error": 0.00011503162751857193,
        "error_type": "SEM",
        "filter_outliers_dict": {
            "filter_outliers": true,
            "iterations": 1,
            "std_devs": 3,
            "use_iqr_filtering": false,
            "use_standard_deviation_filtering": false
        },
        "fit": "linear",
        "fn": 339,
        "include_baseline_error": false,
        "n": 340,
        "outlier_excluded": [
            304
        ],
        "reviewed": true,
        "user_excluded": [],
        "value": 0.002926632986354213
    },
    "Ar37": {
        "error": 0.0157557336822634,
        "error_type": "SEM",
        "filter_outliers_dict": {
            "filter_outliers": true,
            "iterations": 1,
            "std_devs": 3,
            "use_iqr_filtering": false,
            "use_standard_deviation_filtering": false
        },
        "fit": "linear",
        "fn": 340,
        "include_baseline_error": false,
        "n": 340,
        "outlier_excluded": [],
        "reviewed": true,
        "user_excluded": [],
        "value": -0.10115985587202089
    },
    "Ar38": {
        "error": 0.0056047236463702636,
        "error_type": "SEM",
        "filter_outliers_dict": {
            "filter_outliers": true,
            "iterations": 1,
            "std_devs": 3,
            "use_iqr_filtering": false,
            "use_standard_deviation_filtering": false
        },
        "fit": "linear",
        "fn": 340,
        "include_baseline_error": false,
        "n": 340,
        "outlier_excluded": [],
        "reviewed": true,
        "user_excluded": [],
        "value": -0.14537729925729168
    },
    "Ar39": {
        "error": 0.007147291925605122,
        "error_type": "SEM",
        "filter_outliers_dict": {
            "filter_outliers": true,
            "iterations": 1,
            "std_devs": 3,
            "use_iqr_filtering": false,
            "use_standard_deviation_filtering": false
        },
        "fit": "linear",
        "fn": 339,
        "include_baseline_error": false,
        "n": 340,
        "outlier_excluded": [
            62
        ],
        "reviewed": true,
        "user_excluded": [],
        "value": -0.14109632267453448
    },
    "Ar40": {
        "error": 0.015344011547060428,
        "error_type": "SEM",
        "filter_outliers_dict": {
            "filter_outliers": true,
            "iterations": 1,
            "std_devs": 3,
            "use_iqr_filtering": false,
            "use_standard_deviation_filtering": false
        },
        "fit": "linear",
        "fn": 339,
        "include_baseline_error": false,
        "n": 340,
        "outlier_excluded": [
            215
        ],
        "reviewed": true,
        "user_excluded": [],
        "value": 0.343487605993996
    }
}