{
    "Ar36": {
        "error": 0.00015105109041943588,
        "error_type": "SEM",
        "filter_outliers_dict": {
            "filter_outliers": true,
            "iterations": 1,
            "std_devs": 3,
            "use_iqr_filtering": false,
            "use_standard_deviation_filtering": false
        },
        "fit": "linear",
        "fn": 339,
        "include_baseline_error": false,
        "n": 340,
        "outlier_excluded": [
            275
        ],
        "reviewed": true,
        "user_excluded": [],
        "value": 0.006897724349442714
    },
    "Ar37": {
        "error": 0.01581586951307173,
        "error_type": "SEM",
        "filter_outliers_dict": {
            "filter_outliers": true,
            "iterations": 1,
            "std_devs": 3,
            "use_iqr_filtering": false,
            "use_standard_deviation_filtering": false
        },
        "fit": "linear",
        "fn": 339,
        "include_baseline_error": false,
        "n": 340,
        "outlier_excluded": [
            240
        ],
        "reviewed": true,
        "user_excluded": [],
        "value": -0.07798808223360733
    },
    "Ar38": {
        "error": 0.00524145586366615,
        "error_type": "SEM",
        "filter_outliers_dict": {
            "filter_outliers": true,
            "iterations": 1,
            "std_devs": 3,
            "use_iqr_filtering": false,
            "use_standard_deviation_filtering": false
        },
        "fit": "linear",
        "fn": 337,
        "include_baseline_error": false,
        "n": 340,
        "outlier_excluded": [
            75,
            92,
            111
        ],
        "reviewed": true,
        "user_excluded": [],
        "value": -0.13143350022762734
    },
    "Ar39": {
        "error": 0.007883763555245475,
        "error_type": "SEM",
        "filter_outliers_dict": {
            "filter_outliers": true,
            "iterations": 1,
            "std_devs": 3,
            "use_iqr_filtering": false,
            "use_standard_deviation_filtering": false
        },
        "fit": "linear",
        "fn": 339,
        "include_baseline_error": false,
        "n": 340,
        "outlier_excluded": [
            210
        ],
        "reviewed": true,
        "user_excluded": [],
        "value": -0.1427847320791045
    },
    "Ar40": {
        "error": 0.01374942443231152,
        "error_type": "SEM",
        "filter_outliers_dict": {
            "filter_outliers": true,
            "iterations": 1,
            "std_devs": 3,
            "use_iqr_filtering": false,
            "use_standard_deviation_filtering": false
        },
        "fit": "linear",
        "fn": 339,
        "include_baseline_error": false,
        "n": 340,
        "outlier_excluded": [
            39
        ],
        "reviewed": true,
        "user_excluded": [],
        "value": 1.484024191012136
    }
}