{
    "Ar36": {
        "error": 0.00014046992353480354,
        "error_type": "SEM",
        "filter_outliers_dict": {
            "filter_outliers": true,
            "iterations": 2,
            "std_devs": 2
        },
        "fit": "parabolic",
        "value": 0.0014305260516887957
    },
    "Ar37": {
        "error": 0.014812089854166465,
        "error_type": "SEM",
        "filter_outliers_dict": {
            "filter_outliers": true,
            "iterations": 2,
            "std_devs": 2
        },
        "fit": "linear",
        "value": 0.015116031219397946
    },
    "Ar38": {
        "error": 0.004534495080928133,
        "error_type": "SEM",
        "filter_outliers_dict": {
            "filter_outliers": true,
            "iterations": 2,
            "std_devs": 2
        },
        "fit": "linear",
        "value": -0.05810665679547028
    },
    "Ar39": {
        "error": 0.01239272649488161,
        "error_type": "SEM",
        "filter_outliers_dict": {
            "filter_outliers": true,
            "iterations": 2,
            "std_devs": 2
        },
        "fit": "parabolic",
        "value": 0.032978157519145616
    },
    "Ar40": {
        "error": 0.025605338367200293,
        "error_type": "SEM",
        "filter_outliers_dict": {
            "filter_outliers": true,
            "iterations": 2,
            "std_devs": 2
        },
        "fit": "parabolic",
        "value": -0.18726267203820518
    }
}